endgame/__init__.py
endgame/bin/__init__.py
endgame/bin/cli.py
endgame/bin/version.py
endgame/command/__init__.py
endgame/command/expose.py
endgame/command/list_resources.py
endgame/command/smash.py
endgame/exposure_via_aws_ram/__init__.py
endgame/exposure_via_resource_policies/__init__.py
endgame/exposure_via_resource_policies/acm_pca.py
endgame/exposure_via_resource_policies/cloudwatch_logs.py
endgame/exposure_via_resource_policies/common.py
endgame/exposure_via_resource_policies/ecr.py
endgame/exposure_via_resource_policies/efs.py
endgame/exposure_via_resource_policies/elasticsearch.py
endgame/exposure_via_resource_policies/glacier_vault.py
endgame/exposure_via_resource_policies/iam.py
endgame/exposure_via_resource_policies/kms.py
endgame/exposure_via_resource_policies/lambda_function.py
endgame/exposure_via_resource_policies/lambda_layer.py
endgame/exposure_via_resource_policies/s3.py
endgame/exposure_via_resource_policies/secrets_manager.py
endgame/exposure_via_resource_policies/ses.py
endgame/exposure_via_resource_policies/sns.py
endgame/exposure_via_resource_policies/sqs.py
endgame/exposure_via_sharing_apis/__init__.py
endgame/exposure_via_sharing_apis/common.py
endgame/exposure_via_sharing_apis/ebs_snapshots.py
endgame/exposure_via_sharing_apis/ec2_amis.py
endgame/exposure_via_sharing_apis/rds_snapshots.py
endgame/shared/__init__.py
endgame/shared/aws_login.py
endgame/shared/constants.py
endgame/shared/list_resources_response.py
endgame/shared/policy_document.py
endgame/shared/resource_results.py
endgame/shared/response_message.py
endgame/shared/scary_warnings.py
endgame/shared/statement_detail.py
endgame/shared/utils.py
endgame/shared/validate.py
endgame-0.3.0.dist-info/LICENSE
endgame-0.3.0.dist-info/METADATA
endgame-0.3.0.dist-info/WHEEL
endgame-0.3.0.dist-info/entry_points.txt
endgame-0.3.0.dist-info/top_level.txt
endgame-0.3.0.dist-info/zip-safe
endgame-0.3.0.dist-info/RECORD
