Metadata-Version: 2.1
Name: endgame
Version: 0.3.0
Summary: An AWS Pentesting tool that lets you use one-liner commands to backdoor an AWS account's resources with a rogue AWS account - or to the entire internet 😈
Home-page: https://github.com/salesforce/endgame
Author: Kinnaird McQuade
Author-email: kinnairdm@gmail.com
Keywords: aws iam security
Classifier: Programming Language :: Python :: 3
Classifier: License :: OSI Approved :: MIT License
Classifier: Operating System :: OS Independent
Requires-Python: >=3.7
License-File: LICENSE
Requires-Dist: botocore
Requires-Dist: boto3
Requires-Dist: click
Requires-Dist: policy-sentry (>=0.11.5)
Requires-Dist: colorama
